LICENSE
README.rst
setup.cfg
setup.py
orcsome3/__init__.py
orcsome3/version.py
orcsome3-stubs/__init__.py
orcsome3-stubs/version.pyi
orcsome3-stubs/orcsome/__init__.py
orcsome3-stubs/orcsome/__init__.pyi
orcsome3-stubs/orcsome/__main__.pyi
orcsome3-stubs/orcsome/actions.pyi
orcsome3-stubs/orcsome/aliases.pyi
orcsome3-stubs/orcsome/ev.pyi
orcsome3-stubs/orcsome/ev_build.pyi
orcsome3-stubs/orcsome/notify.pyi
orcsome3-stubs/orcsome/run.pyi
orcsome3-stubs/orcsome/utils.pyi
orcsome3-stubs/orcsome/wm.pyi
orcsome3-stubs/orcsome/wrappers.pyi
orcsome3-stubs/orcsome/xlib.pyi
orcsome3-stubs/orcsome/xlib_build.pyi
orcsome3.egg-info/PKG-INFO
orcsome3.egg-info/SOURCES.txt
orcsome3.egg-info/dependency_links.txt
orcsome3.egg-info/not-zip-safe
orcsome3.egg-info/requires.txt
orcsome3.egg-info/top_level.txt
orcsome3/bin/orcsome3
orcsome3/orcsome/__init__.py
orcsome3/orcsome/__main__.py
orcsome3/orcsome/actions.py
orcsome3/orcsome/aliases.py
orcsome3/orcsome/ev.py
orcsome3/orcsome/ev_build.py
orcsome3/orcsome/notify.py
orcsome3/orcsome/run.py
orcsome3/orcsome/utils.py
orcsome3/orcsome/wm.py
orcsome3/orcsome/wrappers.py
orcsome3/orcsome/xlib.py
orcsome3/orcsome/xlib_build.py