Metadata-Version: 2.1
Name: orcsome3
Version: 0.2.0
Summary: Scripting extension for NETWM compliant window managers
Home-page: https://github.com/ahsand97/orcsome3
Author: Ahsan Pérez
Author-email: ahsand.perez@gmail.com
Classifier: Programming Language :: Python :: 3
Classifier: License :: OSI Approved :: MIT License
Classifier: Development Status :: 4 - Beta
Classifier: Environment :: X11 Applications
Classifier: Topic :: Desktop Environment :: Window Managers
Classifier: Intended Audience :: Developers
Classifier: Intended Audience :: End Users/Desktop
Classifier: Natural Language :: English
Requires-Python: >=3.8
Provides-Extra: dev
License-File: LICENSE
